{
    "nrc.ui.modules.value.scale": "المقياس: %s",
    "nrc.ui.modules.value.background": "الخلفية",
    "nrc.ui.modules.value.multiColor": "متعدد الألوان",
    "nrc.ui.modules.value.padding": "الحشو: %s",
    "nrc.ui.modules.value.text": "النص",
    "nrc.ui.modules.value.hideChat": "إخفاء الدردشة",
    "nrc.ui.modules.value.friendNotifications": "إشعارات الأصدقاء",
    "nrc.ui.modules.value.mcRealTimeNotification": "إشعار في الوقت الحقيقي",
    "nrc.ui.modules.value.likeNotification": "إشعار الإعجاب",
    "nrc.ui.modules.value.commentNotification": "إشعار التعليق",
    "nrc.ui.modules.value.statusChangeNotifications": "إشعارات تغيير الحالة",
    "nrc.ui.modules.value.time": "الوقت",
    "nrc.ui.modules.value.weather": "الطقس",
    "nrc.ui.modules.value.f5": "F5",
    "nrc.ui.modules.value.chat": "الدردشة",
    "nrc.ui.modules.value.inventory": "المخزون",
    "nrc.ui.modules.value.scoreboard": "لوحة النتائج",
    "nrc.ui.modules.value.pingKey": "مفتاح التنبيه",
    "nrc.ui.modules.value.showDetails": "إظهار التفاصيل",
    "nrc.ui.modules.value.showCreator": "إظهار المنشئ",
    "nrc.ui.modules.value.showRemainingTime": "إظهار الوقت المتبقي",
    "nrc.ui.modules.value.pingScale": "مقياس التنبيه",
    "nrc.ui.modules.value.ownPingColor": "لون التنبيه الخاص",
    "nrc.ui.modules.value.pingLifetime": "عمر التنبيه",
    "nrc.ui.modules.value.zoomKey": "مفتاح التكبير",
    "nrc.ui.modules.value.enableScrolling": "تمكين التمرير",
    "nrc.ui.modules.value.smoothCamera": "الكاميرا السلسة",
    "nrc.ui.modules.value.smoothZoom": "التكبير السلس",
    "nrc.ui.modules.value.zoomInDuration": "مدة التكبير",
    "nrc.ui.modules.value.zoomOutDuration": "مدة التصغير",
    "nrc.ui.modules.value.scrollStrength": "قوة التمرير",
    "nrc.ui.modules.value.easing": "التيسير",
    "nrc.ui.modules.value.async": "غير متزامن",
    "nrc.ui.modules.value.copyToClipboard": "نسخ إلى الحافظة",
    "nrc.ui.modules.value.imageHoster": "مضيف الصور",
    "nrc.ui.modules.value.apiKey": "مفتاح API",
    "nrc.ui.modules.value.openAfterUpload": "فتح بعد التحميل",
    "nrc.ui.modules.value.disableLavaFog": "تعطيل ضباب الحمم",
    "nrc.ui.modules.value.disableWaterFog": "تعطيل ضباب الماء",
    "nrc.ui.modules.value.disablePowderSnow": "تعطيل الثلج المسحوق",
    "nrc.ui.modules.value.disableTerrainFog": "تعطيل ضباب التضاريس",
    "nrc.ui.modules.value.fogEndDistance": "مسافة نهاية الضباب",
    "nrc.ui.modules.value.size": "الحجم",
    "nrc.ui.modules.value.margin": "الهامش",
    "nrc.ui.modules.value.position": "الموقع",
    "nrc.ui.modules.value.iconVariation": "تنوع الأيقونة",
    "nrc.ui.modules.value.iconPosition": "موضع الأيقونة",
    "nrc.ui.modules.value.key": "المفتاح",
    "nrc.ui.modules.value.format": "التنسيق",
    "nrc.ui.modules.value.coloredLabel": "تسمية ملونة",
    "nrc.ui.modules.value.showX": "إظهار X",
    "nrc.ui.modules.value.showY": "إظهار Y",
    "nrc.ui.modules.value.showZ": "إظهار Z",
    "nrc.ui.modules.value.showBiome": "إظهار البيوم",
    "nrc.ui.modules.value.showDirection": "إظهار الاتجاه",
    "nrc.ui.modules.value.swingDuration": "مدة التأرجح",
    "nrc.ui.modules.value.noDamageTilt": "لا يوجد ميل للضرر",
    "nrc.ui.modules.value.damageTiltModifier": "تعديل ميل الضرر",
    "nrc.ui.modules.value.oldSneak": "الاختباء القديم",
    "nrc.ui.modules.value.noBob": "لا تمايل",
    "nrc.ui.modules.value.noCrosshairBob": "لا تمايل للشبكة",
    "nrc.ui.modules.value.color": "اللون",
    "nrc.ui.modules.value.rgb": "RGB",
    "nrc.ui.modules.value.width": "العرض",
    "nrc.ui.modules.value.noOutline": "بدون مخطط",
    "nrc.ui.modules.value.vertical": "عمودي",
    "nrc.ui.modules.value.leftText": "النص الأيسر",
    "nrc.ui.modules.value.showHelmet": "إظهار الخوذة",
    "nrc.ui.modules.value.showChestplate": "إظهار الدرع الصدري",
    "nrc.ui.modules.value.showLeggings": "إظهار البنطال",
    "nrc.ui.modules.value.showBoots": "إظهار الأحذية",
    "nrc.ui.modules.value.showHeldItem": "إظهار العنصر المحمول",
    "nrc.ui.modules.value.showOffHandItem": "إظهار العنصر في اليد الثانوية",
    "nrc.ui.modules.value.showItemDamage": "إظهار ضرر العنصر",
    "nrc.ui.modules.value.showDamageOverlay": "إظهار تراكب الضرر",
    "nrc.ui.modules.value.keyGap": "الفجوة بين المفاتيح",
    "nrc.ui.modules.value.pressBackgroundColor": "لون خلفية الضغط",
    "nrc.ui.modules.value.pressTextColor": "لون نص الضغط",
    "nrc.ui.modules.value.showMouse": "إظهار الفأرة",
    "nrc.ui.modules.value.showCps": "إظهار CPS",
    "nrc.ui.modules.value.showSpaceBar": "إظهار مفتاح المسافة",
    "nrc.ui.modules.value.stackMessages": "تكديس الرسائل",
    "nrc.ui.modules.value.keepMessageOnClose": "الاحتفاظ بالرسالة عند الإغلاق",
    "nrc.ui.modules.value.historyLimit": "حد السجل",
    "nrc.ui.modules.value.style": "النمط",
    "nrc.ui.modules.value.gap": "الفجوة",
    "nrc.ui.modules.value.thickness": "السُمك",
    "nrc.ui.modules.value.rotation": "الدوران",
    "nrc.ui.modules.value.outline": "الخط الخارجي",
    "nrc.ui.modules.value.outlineColor": "لون الخط الخارجي",
    "nrc.ui.modules.value.dot": "النقطة",
    "nrc.ui.modules.value.dotColor": "لون النقطة",
    "nrc.ui.modules.value.lowFire": "نار منخفضة",
    "nrc.ui.modules.value.lowFireHeight": "ارتفاع النار المنخفضة",
    "nrc.ui.modules.value.hidePumpkinOverlay": "إخفاء تراكب القرع",
    "nrc.ui.modules.value.hideIncompatibles": "إخفاء العناصر غير المتوافقة",
    "nrc.ui.modules.value.armorOpacity": "شفافية الدرع",
    "nrc.ui.modules.value.crosshairCursor": "مؤشر الشعيرات المتقاطعة",
    "nrc.ui.modules.value.lowerShields": "خفض الدروع",
    "nrc.ui.modules.value.mainHandHeight": "ارتفاع اليد الرئيسية",
    "nrc.ui.modules.value.offHandHeight": "ارتفاع اليد الثانوية",
    "nrc.ui.modules.value.effect": "التأثير",
    "nrc.ui.modules.value.self": "الذات",
    "nrc.ui.modules.value.players": "اللاعبين",
    "nrc.ui.modules.value.mobs": "الكائنات الحية",
    "nrc.ui.modules.value.others": "الآخرين",
    "nrc.ui.modules.value.strength": "القوة",
    "nrc.ui.modules.value.inGui": "في الواجهة الرسومية",
    "nrc.ui.modules.value.fontColor": "لون الخط",
    "nrc.ui.modules.value.headerColor": "لون الرأس",
    "nrc.ui.modules.value.backgroundColor": "لون الخلفية",
    
    "nrc.ui.modules.button.tooltip.apply_all": "تطبيق التغييرات عالميًا",
    
    "nrc.generic.error.user_not_found": "لم يتم العثور على المستخدم.",
    "nrc.generic.errors.no_valid_uuid": "UUID غير صالح.",
    "nrc.generic.errors.cooldown": "هدئ أعصابك... لمدة %s ثانية",
    
    "norisk.generic.ui.cancel": "إلغاء",
    "norisk.generic.ui.confirm": "حسنًا!",
  
    "nrc.friends.notification.friend_online": "%s متصل الآن",
    "nrc.friends.notification.friend_offline": "%s غير متصل الآن",
  
    "nrc.friends.action.remove_friend": "إزالة الصديق",
    "nrc.friends.action.toggle_ping": "تبديل التنبيه",
  
    "nrc.friends.wheel.action.copy_cape": "",
    "nrc.friends.wheel.action.settings": "الإعدادات",
    "nrc.friends.wheel.action.add_friend": "إضافة صديق",
    "nrc.friends.wheel.action.remove_friend": "إزالة الصديق",
    "nrc.friends.wheel.ui.add_action": "إضافة إجراء...",
    "nrc.friends.wheel.ui.rename_action": "إعادة التسمية...",
    "nrc.friends.wheel.ui.rename_command": "إعادة التسمية...",
    "nrc.friends.wheel.ui.tooltip.command_action": "سيتم تنفيذ الأمر التالي %s",
  
    "nrc.friends.errors.friend_not_found": "لم يتم العثور على الصديق",
    "nrc.friends.errors.cant_be_friends_with_yourself": "لا يمكنك أن تكون صديقًا لنفسك",
    "nrc.friends.errors.already_friends_with": "أنت بالفعل صديق مع %s",
    "nrc.friends.errors.request_pending": "الطلب المرسل إلى %s معلق",
    "nrc.friends.errors.max_ping_size": "تم الوصول إلى الحد الأقصى لحجم التنبيه",
  
    "nrc.friends.tooltip.ping_enabled": "التنبيه ممكن: %s",
    "nrc.friends.tooltip.ping_disabled": "التنبيه معطل: %s",
  
    "nrc.friends.request.received.accepted": "%s قد قبل طلب صداقتك",
    "nrc.friends.request.received.denied": "%s قد رفض طلب صداقتك",
    "nrc.friends.request.received.pending": "%s قد أرسل إليك طلب صداقة",
    "nrc.friends.request.received.withdrawn": "%s قد سحب طلب الصداقة",
  
    "nrc.friends.request.sent.accepted": "لقد قبلت طلب صداقة %s",
    "nrc.friends.request.sent.denied": "لقد رفضت طلب صداقة %s",
    "nrc.friends.request.sent.pending": "لقد أرسلت طلب صداقة إلى %s",
    "nrc.friends.request.sent.withdrawn": "لقد سحبت طلب صداقتك إلى %s",
  
    "nrc.friends.request.ui.outgoing": "معلق",
    "nrc.friends.request.ui.incoming": "طلب صداقة",
    "nrc.friends.request.ui.add_friend": "إضافة صديق...",

    "nrc.friends.offline.seconds": "غير متصل لمدة %s ثانية",
    "nrc.friends.offline.minutes": "غير متصل لمدة %s دقيقة",
    "nrc.friends.offline.hours": "غير متصل لمدة %s ساعة",
    "nrc.friends.offline.days": "غير متصل لمدة %s يوم",
  
    "nrc.friends.tab.friend": "%s أصدقاء",
    "nrc.friends.tab.incoming": "%s طلبات",
    "nrc.friends.tab.outgoing": "%s معلق",
  
    "nrc.friends.host_world": "استضافة العالم",
    "nrc.friends.host.world_options": "خيارات العالم",
    "nrc.friends.host.gamemode": "وضع اللعبة",
    "nrc.friends.host.hosting_success": "تم استضافة العالم بنجاح على المنفذ %s",
    "nrc.friends.host.hosting_success_friends_invite_info": "يمكنك الآن دعوة الأصدقاء",
    "nrc.friends.host.hosting_success_friends_invite_info_click": "[اضغط]",
    "nrc.friends.host.hosting_success_friends_invite_info_copy_url": "[نسخ الرابط]",
    "nrc.friends.host.hosting_error": "خطأ في استضافة العالم، يرجى المحاولة مرة أخرى :/",
    "nrc.friends.host.stop_world_success": "تم إغلاق العالم بنجاح على المنفذ %s",
    "nrc.friends.host.stop_world": "إغلاق العالم",
    "nrc.friends.host.invite_friend": "دعوة إلى العالم",
    "nrc.friends.host.invite_success": "لقد دعوت %s إلى عالمك",
  
    "nrc.cosmetics.ui.search_cosmetic": "بحث...",
    "nrc.cosmetics.ui.create_outfit": "\uD83D\uDC55 إنشاء زي",
    "nrc.cosmetics.ui.gift_cosmetic": "✨ هدية تجميلية",
    "nrc.cosmetics.ui.enter_user": "أدخل اسم المستخدم...",
    "nrc.cosmetics.ui.tooltip.options": "خيارات",
    "nrc.cosmetics.ui.edit_outfit": "✎ تعديل",
    "nrc.cosmetics.ui.delete_outfit": "\uD83D\uDDD1 حذف",
    "nrc.cosmetics.ui.rename_outfit": "✎ إعادة تسمية الزي",
    "nrc.cosmetics.ui.edit_skin": "✎ تعديل",
    "nrc.cosmetics.ui.delete_skin": "\uD83D\uDDD1 حذف",
    "nrc.cosmetics.ui.save": "حفظ",
    "nrc.cosmetics.ui.cancel": "إلغاء",
    "nrc.cosmetics.ui.steal_skin_by_username": "سرقة الجلد من اسم المستخدم",
    "nrc.cosmetics.ui.steal_skin_by_url": "تحميل الجلد من رابط",
    "nrc.cosmetics.ui.add_skins": "＋ إضافة جلد",
    "nrc.cosmetics.ui.missing_coins": "لا يوجد ما يكفي من العملات",
    "nrc.cosmetics.ui.confirm_buy": "شراء",
    "nrc.cosmetics.ui.undo": "تراجع",
    "nrc.cosmetics.ui.unowned_items_dialog_closed_title": "عناصر غير مملوكة مجهزة...",
    "nrc.cosmetics.ui.unowned_items_dialog_closed_base": "العناصر غير المملوكة لن تكون مرئية في اللعبة.",
    "nrc.cosmetics.ui.free": "مجاني",
    "nrc.cosmetics.update.generic": "تم تلقي تحديث تجميلي :)!",
    "nrc.cosmetics.update.positive": "تم تلقي تحديث تجميلي %s :)!",
    "nrc.cosmetics.update.negative": "تم سحب العنصر التجميلي %s :)!",
  
    "nrc.cosmetics.ui.tooltip.owned": "مملوك",
    "nrc.cosmetics.ui.tooltip.missing_cosmetics": "يحتوي على عناصر غير مملوكة",
    "nrc.cosmetics.ui.tooltip.edit_cosmetic": "تعديل",
  
    "nrc.cosmetics.enum.filter.all": "الكل",
    "nrc.cosmetics.enum.filter.alphabet": "الحروف الأبجدية",
    "nrc.cosmetics.enum.filter.price": "السعر",
    "nrc.cosmetics.enum.filter.owned": "مملوك",
    "nrc.cosmetics.enum.skinaddoption.username": "\uD83D\uDE0A مستخدم",
    "nrc.cosmetics.enum.skinaddoption.url": "\uD83D\uDD17 رابط",
  
    "norisk.screenshot.taken": "تم حفظ لقطة الشاشة.",
    "norisk.screenshot.upload.start": "جارٍ تحميل لقطة الشاشة مع %s",
    "norisk.screenshot.upload.done": "تم تحميل لقطة الشاشة بنجاح",
    "norisk.screenshot.action.upload": "[تحميل]",
    "norisk.screenshot.upload.error.missing_url": "تعذر تحميل لقطة الشاشة: الرابط مفقود",
    "norisk.screenshot.upload.error.doesnt_exist": "تعذر تحميل لقطة الشاشة: الملف غير موجود",
    "norisk.screenshot.action.open": "[فتح]",
    "norisk.screenshot.open.error.doesnt_exist": "تعذر فتح لقطة الشاشة: الملف غير موجود",
    "norisk.screenshot.action.copy": "[نسخ]",
    "norisk.screenshot.copy.success": "تم نسخ لقطة الشاشة إلى الحافظة",
    "norisk.screenshot.copy.error.doesnt_exist": "تعذر نسخ لقطة الشاشة: الملف غير موجود",
    "norisk.screenshot.action.delete": "[حذف]",
    "norisk.screenshot.delete.error.doesnt_exist": "تعذر حذف لقطة الشاشة: الملف غير موجود",
    "norisk.screenshot.delete.success": "تم حذف لقطة الشاشة بنجاح",
    "norisk.clock.tooltip.E": "اسم اليوم",
    "norisk.clock.tooltip.dd": "اليوم في الشهر",
    "norisk.clock.tooltip.MM": "الشهر في السنة",
    "norisk.clock.tooltip.MMMM": "اسم الشهر في السنة",
    "norisk.clock.tooltip.yyyy": "السنة",
    "norisk.clock.tooltip.HH": "الساعة في اليوم",
    "norisk.clock.tooltip.mm": "الدقيقة في الساعة",
    "norisk.clock.tooltip.ss": "الثانية في الدقيقة",
    "norisk.clock.tooltip.more_info": "لمزيد من المعلومات: ابحث في جوجل 'Java SimpleDateFormat'",
  
    "norisk.tebex.coin-purchase": "لقد تلقيت %s عملات",
    "norisk.cosmetics.outfit.toast.cosmeticsettings.saved": "تم حفظ إعدادات العنصر التجميلي.",
    "nrc.friends.stop_world": "إيقاف العالم",
    "nrc.ui.modules.value.showServer":"عرض الخادم",
    "nrc.ui.modules.value.showIpAddress":"عرض عنوان IP",
    "nrc.ui.modules.value.showPort":"عرض المنفذ",
  
    "mcreal.browse.label.friends": "أصدقائي",
    "mcreal.browse.label.discovery": "اكتشاف",
    "mcreal.browse.label.nothing": "لا يوجد شيء لرؤيته :(",
    "mcreal.browse.label.your_turn": "انقر هنا لتكون الأول في نشر McReal!",
    "mcreal.browse.label.create_post": "إنشاء منشور",
    "mcreal.browse.label.all_posts_fetched": "لا توجد منشورات جديدة :(",
    "mcreal.browse.label.unlock": "ارفع لتحميل عرض الآخرين",
    "mcreal.browse.label.post_deleted_unlock": "تم حذف منشورك",
    "mcreal.browse.button.load_more": "تحميل المزيد",
    "mcreal.browse.label.your_post": "McReal الخاص بك",
    "mcreal.browse.label.show_comments": "%s تعليقات",
    "mcreal.post.delete.request": "هل أنت متأكد من حذف منشورك؟",
    "mcreal.post.delete.success": "تم حذف McReal الخاص بك بنجاح",
    "mcreal.post.delete.error": "خطأ في حذف McReal الخاص بك %s",
    "mcreal.report.success": "شكرًا لمساعدتك!",
    "mcreal.report.error": "خطأ في التقرير %s",
    "mcreal.report.button.confirm": "تقرير",
    "mcreal.report.label.type": "تقرير %s",
    "mcreal.report.label.info": "ماذا حدث؟",
    "mcreal.report.label.obscenity": "الفحش",
    "mcreal.report.label.hate_speech": "خطاب الكراهية",
    "mcreal.report.label.copyright_infringement": "انتهاك حقوق الطبع والنشر",
    "mcreal.report.label.privacy_violation": "انتهاك الخصوصية",
    "mcreal.report.label.spam_or_fraud": "البريد العشوائي أو الاحتيال",
    "mcreal.report.label.inappropriate_for_minors": "غير مناسب للقاصرين",
    "mcreal.report.label.other": "أخرى",
    "mcreal.pin.request": "هل تريد تثبيت منشور اليوم الخاص بك؟",
    "mcreal.pin.delete_request": "هل تريد حذف منشورك المثبت؟",
    "mcreal.browse.button.reply": "رد",
    "norisk.ui.confirm": "تأكيد",
    "norisk.ui.cancel": "إلغاء",
    "mcreal.activated": "ارفع McReal باستخدام F2!",
    "mcreal.notification": "وقت McReal",
    "mcreal.saved": "تم حفظ McReal",
    "mcreal.upload.success": "تم رفع McReal بنجاح.",
    "mcreal.upload.error": "حدث خطأ أثناء رفع McReal %s",
    "mcreal.upload.show_others": "[عرض الآخرين]",
    "mcreal.upload.label.title": "العنوان",
    "mcreal.upload.label.server_ip": "عنوان الخادم IP",
    "mcreal.upload.label.friends_only": "للأصدقاء فقط",
    "mcreal.upload.label.upload": "رفع"
}
